package/main.py
package/assets/__init__.py
package/components/__init__.py
package/components/model.py
package/layout/__init__.py
package/layout/layout.py
package/utils/__init__.py
package/utils/constraints.py
package/utils/functions.py
package/utils/get_master_data.py
input_svrp_v3-2.3.dist-info/LICENSE
input_svrp_v3-2.3.dist-info/METADATA
input_svrp_v3-2.3.dist-info/WHEEL
input_svrp_v3-2.3.dist-info/top_level.txt
input_svrp_v3-2.3.dist-info/RECORD
